{
    "$schema": "http://json-schema.org/draft-04/schema#",
    "description": "",
    "type": "object",
    "properties": {
        "id": {
            "type": "string",
            "minLength": 1
        },
        "object": {
            "type": "string",
            "minLength": 1
        },
        "api_version": {
            "type": "string",
            "minLength": 1
        },
        "created": {
            "type": "number"
        },
        "data": {
            "type": "object",
            "properties": {
                "object": {
                    "type": "object",
                    "properties": {
                        "id": {
                            "type": "string",
                            "minLength": 1
                        },
                        "object": {
                            "type": "string",
                            "minLength": 1
                        },
                        "adaptive_pricing": {
                            "type": "object",
                            "properties": {
                                "enabled": {
                                    "type": "boolean"
                                }
                            },
                            "required": [
                                "enabled"
                            ]
                        },
                        "after_expiration": {
                            "type": "object",
                            "properties": {},
                            "required": []
                        },
                        "allow_promotion_codes": {
                            "type": "boolean"
                        },
                        "amount_subtotal": {
                            "type": "number"
                        },
                        "amount_total": {
                            "type": "number"
                        },
                        "automatic_tax": {
                            "type": "object",
                            "properties": {
                                "enabled": {
                                    "type": "boolean"
                                },
                                "liability": {
                                    "type": "object",
                                    "properties": {},
                                    "required": []
                                },
                                "status": {
                                    "type": "object",
                                    "properties": {},
                                    "required": []
                                }
                            },
                            "required": [
                                "enabled",
                                "liability",
                                "status"
                            ]
                        },
                        "billing_address_collection": {
                            "type": "string",
                            "minLength": 1
                        },
                        "cancel_url": {
                            "type": "string",
                            "minLength": 1
                        },
                        "client_reference_id": {
                            "type": "object",
                            "properties": {},
                            "required": []
                        },
                        "client_secret": {
                            "type": "object",
                            "properties": {},
                            "required": []
                        },
                        "consent": {
                            "type": "object",
                            "properties": {},
                            "required": []
                        },
                        "consent_collection": {
                            "type": "object",
                            "properties": {
                                "payment_method_reuse_agreement": {
                                    "type": "object",
                                    "properties": {},
                                    "required": []
                                },
                                "promotions": {
                                    "type": "string",
                                    "minLength": 1
                                },
                                "terms_of_service": {
                                    "type": "string",
                                    "minLength": 1
                                }
                            },
                            "required": [
                                "payment_method_reuse_agreement",
                                "promotions",
                                "terms_of_service"
                            ]
                        },
                        "created": {
                            "type": "number"
                        },
                        "currency": {
                            "type": "string",
                            "minLength": 1
                        },
                        "currency_conversion": {
                            "type": "object",
                            "properties": {},
                            "required": []
                        },
                        "custom_fields": {
                            "type": "array",
                            "items": {
                                "required": [],
                                "properties": {}
                            }
                        },
                        "custom_text": {
                            "type": "object",
                            "properties": {
                                "after_submit": {
                                    "type": "object",
                                    "properties": {},
                                    "required": []
                                },
                                "shipping_address": {
                                    "type": "object",
                                    "properties": {},
                                    "required": []
                                },
                                "submit": {
                                    "type": "object",
                                    "properties": {},
                                    "required": []
                                },
                                "terms_of_service_acceptance": {
                                    "type": "object",
                                    "properties": {},
                                    "required": []
                                }
                            },
                            "required": [
                                "after_submit",
                                "shipping_address",
                                "submit",
                                "terms_of_service_acceptance"
                            ]
                        },
                        "customer": {
                            "type": "object",
                            "properties": {},
                            "required": []
                        },
                        "customer_creation": {
                            "type": "string",
                            "minLength": 1
                        },
                        "customer_details": {
                            "type": "object",
                            "properties": {
                                "address": {
                                    "type": "object",
                                    "properties": {
                                        "city": {
                                            "type": "string",
                                            "minLength": 1
                                        },
                                        "country": {
                                            "type": "string",
                                            "minLength": 1
                                        },
                                        "line1": {
                                            "type": "string",
                                            "minLength": 1
                                        },
                                        "line2": {
                                            "type": "object",
                                            "properties": {},
                                            "required": []
                                        },
                                        "postal_code": {
                                            "type": "string",
                                            "minLength": 1
                                        },
                                        "state": {
                                            "type": "string",
                                            "minLength": 1
                                        }
                                    },
                                    "required": [
                                        "city",
                                        "country",
                                        "line1",
                                        "line2",
                                        "postal_code",
                                        "state"
                                    ]
                                },
                                "email": {
                                    "type": "string",
                                    "minLength": 1
                                },
                                "name": {
                                    "type": "string",
                                    "minLength": 1
                                },
                                "phone": {
                                    "type": "object",
                                    "properties": {},
                                    "required": []
                                },
                                "tax_exempt": {
                                    "type": "string",
                                    "minLength": 1
                                },
                                "tax_ids": {
                                    "type": "array",
                                    "items": {
                                        "required": [],
                                        "properties": {}
                                    }
                                }
                            },
                            "required": [
                                "address",
                                "email",
                                "name",
                                "phone",
                                "tax_exempt",
                                "tax_ids"
                            ]
                        },
                        "customer_email": {
                            "type": "object",
                            "properties": {},
                            "required": []
                        },
                        "expires_at": {
                            "type": "number"
                        },
                        "invoice": {
                            "type": "object",
                            "properties": {},
                            "required": []
                        },
                        "invoice_creation": {
                            "type": "object",
                            "properties": {
                                "enabled": {
                                    "type": "boolean"
                                },
                                "invoice_data": {
                                    "type": "object",
                                    "properties": {
                                        "account_tax_ids": {
                                            "type": "object",
                                            "properties": {},
                                            "required": []
                                        },
                                        "custom_fields": {
                                            "type": "object",
                                            "properties": {},
                                            "required": []
                                        },
                                        "description": {
                                            "type": "object",
                                            "properties": {},
                                            "required": []
                                        },
                                        "footer": {
                                            "type": "object",
                                            "properties": {},
                                            "required": []
                                        },
                                        "issuer": {
                                            "type": "object",
                                            "properties": {},
                                            "required": []
                                        },
                                        "metadata": {
                                            "type": "object",
                                            "properties": {},
                                            "required": []
                                        },
                                        "rendering_options": {
                                            "type": "object",
                                            "properties": {},
                                            "required": []
                                        }
                                    },
                                    "required": [
                                        "account_tax_ids",
                                        "custom_fields",
                                        "description",
                                        "footer",
                                        "issuer",
                                        "metadata",
                                        "rendering_options"
                                    ]
                                }
                            },
                            "required": [
                                "enabled",
                                "invoice_data"
                            ]
                        },
                        "livemode": {
                            "type": "boolean"
                        },
                        "locale": {
                            "type": "string",
                            "minLength": 1
                        },
                        "metadata": {
                            "type": "object",
                            "properties": {
                                "CAMPAINGID": {
                                    "type": "string",
                                    "minLength": 1
                                }
                            },
                            "required": [
                                "CAMPAINGID"
                            ]
                        },
                        "mode": {
                            "type": "string",
                            "minLength": 1
                        },
                        "payment_intent": {
                            "type": "string",
                            "minLength": 1
                        },
                        "payment_link": {
                            "type": "string",
                            "minLength": 1
                        },
                        "payment_method_collection": {
                            "type": "string",
                            "minLength": 1
                        },
                        "payment_method_configuration_details": {
                            "type": "object",
                            "properties": {
                                "id": {
                                    "type": "string",
                                    "minLength": 1
                                },
                                "parent": {
                                    "type": "object",
                                    "properties": {},
                                    "required": []
                                }
                            },
                            "required": [
                                "id",
                                "parent"
                            ]
                        },
                        "payment_method_options": {
                            "type": "object",
                            "properties": {
                                "card": {
                                    "type": "object",
                                    "properties": {
                                        "request_three_d_secure": {
                                            "type": "string",
                                            "minLength": 1
                                        }
                                    },
                                    "required": [
                                        "request_three_d_secure"
                                    ]
                                }
                            },
                            "required": [
                                "card"
                            ]
                        },
                        "payment_method_types": {
                            "type": "array",
                            "items": {
                                "required": [],
                                "properties": {}
                            }
                        },
                        "payment_status": {
                            "type": "string",
                            "minLength": 1
                        },
                        "phone_number_collection": {
                            "type": "object",
                            "properties": {
                                "enabled": {
                                    "type": "boolean"
                                }
                            },
                            "required": [
                                "enabled"
                            ]
                        },
                        "recovered_from": {
                            "type": "object",
                            "properties": {},
                            "required": []
                        },
                        "saved_payment_method_options": {
                            "type": "object",
                            "properties": {},
                            "required": []
                        },
                        "setup_intent": {
                            "type": "object",
                            "properties": {},
                            "required": []
                        },
                        "shipping_address_collection": {
                            "type": "object",
                            "properties": {},
                            "required": []
                        },
                        "shipping_cost": {
                            "type": "object",
                            "properties": {},
                            "required": []
                        },
                        "shipping_details": {
                            "type": "object",
                            "properties": {},
                            "required": []
                        },
                        "shipping_options": {
                            "type": "array",
                            "items": {
                                "required": [],
                                "properties": {}
                            }
                        },
                        "status": {
                            "type": "string",
                            "minLength": 1
                        },
                        "submit_type": {
                            "type": "string",
                            "minLength": 1
                        },
                        "subscription": {
                            "type": "object",
                            "properties": {},
                            "required": []
                        },
                        "success_url": {
                            "type": "string",
                            "minLength": 1
                        },
                        "tax_id_collection": {
                            "type": "object",
                            "properties": {
                                "enabled": {
                                    "type": "boolean"
                                },
                                "required": {
                                    "type": "string",
                                    "minLength": 1
                                }
                            },
                            "required": [
                                "enabled",
                                "required"
                            ]
                        },
                        "total_details": {
                            "type": "object",
                            "properties": {
                                "amount_discount": {
                                    "type": "number"
                                },
                                "amount_shipping": {
                                    "type": "number"
                                },
                                "amount_tax": {
                                    "type": "number"
                                }
                            },
                            "required": [
                                "amount_discount",
                                "amount_shipping",
                                "amount_tax"
                            ]
                        },
                        "ui_mode": {
                            "type": "string",
                            "minLength": 1
                        },
                        "url": {
                            "type": "object",
                            "properties": {},
                            "required": []
                        }
                    },
                    "required": [
                        "id",
                        "object",
                        "adaptive_pricing",
                        "after_expiration",
                        "allow_promotion_codes",
                        "amount_subtotal",
                        "amount_total",
                        "automatic_tax",
                        "billing_address_collection",
                        "cancel_url",
                        "client_reference_id",
                        "client_secret",
                        "consent",
                        "consent_collection",
                        "created",
                        "currency",
                        "currency_conversion",
                        "custom_fields",
                        "custom_text",
                        "customer",
                        "customer_creation",
                        "customer_details",
                        "customer_email",
                        "expires_at",
                        "invoice",
                        "invoice_creation",
                        "livemode",
                        "locale",
                        "metadata",
                        "mode",
                        "payment_intent",
                        "payment_link",
                        "payment_method_collection",
                        "payment_method_configuration_details",
                        "payment_method_options",
                        "payment_method_types",
                        "payment_status",
                        "phone_number_collection",
                        "recovered_from",
                        "saved_payment_method_options",
                        "setup_intent",
                        "shipping_address_collection",
                        "shipping_cost",
                        "shipping_details",
                        "shipping_options",
                        "status",
                        "submit_type",
                        "subscription",
                        "success_url",
                        "tax_id_collection",
                        "total_details",
                        "ui_mode",
                        "url"
                    ]
                }
            },
            "required": [
                "object"
            ]
        },
        "livemode": {
            "type": "boolean"
        },
        "pending_webhooks": {
            "type": "number"
        },
        "request": {
            "type": "object",
            "properties": {
                "id": {
                    "type": "object",
                    "properties": {},
                    "required": []
                },
                "idempotency_key": {
                    "type": "object",
                    "properties": {},
                    "required": []
                }
            },
            "required": [
                "id",
                "idempotency_key"
            ]
        },
        "type": {
            "type": "string",
            "minLength": 1
        }
    },
    "required": [
        "id",
        "object",
        "api_version",
        "created",
        "data",
        "livemode",
        "pending_webhooks",
        "request",
        "type"
    ]
}